{"status": "success", "data": [{"bus": "JTA4500", "route": ["BP001"], "timestamp": "2023-03-22 16:28:51", "latitude": 1.853436, "longitude": 102.926979, "speed": 0, "bearing": 243}, {"bus": "JTA5200", "route": ["BP002"], "timestamp": "2023-03-29 19:18:02", "latitude": 1.857663, "longitude": 102.935242, "speed": 49, "bearing": 287}, {"bus": "JVQ8400", "route": ["HSA"], "timestamp": "2023-03-29 19:15:28", "latitude": 1.490647, "longitude": 103.7239, "speed": 3, "bearing": 276}, {"bus": "JVU8700", "route": ["HSA"], "timestamp": "2023-03-29 19:30:16", "latitude": 1.516037, "longitude": 103.699188, "speed": 0, "bearing": 329}, {"bus": "JVR8900", "route": ["HSA"], "timestamp": "2023-03-16 22:34:36", "latitude": 1.490823, "longitude": 103.724052, "speed": 0, "bearing": 329}, {"bus": "JVQ8500", "route": ["HSI"], "timestamp": "2023-03-29 20:32:37", "latitude": 1.484261, "longitude": 103.636436, "speed": 0, "bearing": 244}, {"bus": "JQU5455", "route": ["KL001"], "timestamp": "2023-03-29 11:46:09", "latitude": 2.062842, "longitude": 103.30928, "speed": 1, "bearing": 167}, {"bus": "JNT7334", "route": ["KL002"], "timestamp": "2023-03-29 21:01:54", "latitude": 2.010994, "longitude": 103.288071, "speed": 0, "bearing": 55}, {"bus": "JTU1300", "route": ["KT001"], "timestamp": "2023-03-29 19:28:15", "latitude": 1.721902, "longitude": 103.878914, "speed": 24, "bearing": 324}, {"bus": "JTV3600", "route": ["KT002"], "timestamp": "2023-03-24 20:04:30", "latitude": 1.716362, "longitude": 103.965851, "speed": 58, "bearing": 91}, {"bus": "BKN6733", "route": ["LB001", "LB001A", "LB002"], "timestamp": "2023-03-29 18:41:19", "latitude": 2.385019, "longitude": 103.021812, "speed": 1, "bearing": 202}, {"bus": "JTU5264", "route": ["ME001"], "timestamp": "2023-03-29 19:51:27", "latitude": 1.534606, "longitude": 103.744576, "speed": 0, "bearing": 248}, {"bus": "JTU4290", "route": ["ME002"], "timestamp": "2023-03-29 19:43:20", "latitude": 2.435663, "longitude": 103.83844, "speed": 10, "bearing": 223}, {"bus": "JSM5469", "route": ["ME003"], "timestamp": "2023-03-29 20:08:26", "latitude": 2.431228, "longitude": 103.833176, "speed": 0, "bearing": 231}, {"bus": "VAC7800", "route": ["MU001"], "timestamp": "2023-03-29 19:01:37", "latitude": 2.047057, "longitude": 102.565605, "speed": 30, "bearing": 52}, {"bus": "JSB2100", "route": ["MU002"], "timestamp": "2023-03-29 19:01:01", "latitude": 2.09031, "longitude": 102.621086, "speed": 2, "bearing": 254}, {"bus": "JSD7100", "route": ["MU003"], "timestamp": "2023-03-29 18:49:51", "latitude": 2.047466, "longitude": 102.599884, "speed": 27, "bearing": 275}, {"bus": "JTP9500", "route": ["MU004"], "timestamp": "2023-03-29 21:45:00", "latitude": 2.090325, "longitude": 102.621056, "speed": 2, "bearing": 338}, {"bus": "JVH2400", "route": ["MU005"], "timestamp": "2023-03-29 22:08:33", "latitude": 2.093991, "longitude": 102.620064, "speed": 9, "bearing": 331}, {"bus": "JSN517", "route": ["P101"], "timestamp": "2023-03-29 23:49:50", "latitude": 1.537511, "longitude": 103.75248, "speed": 12, "bearing": 50}, {"bus": "JSN7055", "route": ["P101"], "timestamp": "2023-03-30 01:00:44", "latitude": 1.53719, "longitude": 103.75235, "speed": 0, "bearing": 0}, {"bus": "JSP845", "route": ["P101"], "timestamp": "2023-03-30 01:04:20", "latitude": 1.537714, "longitude": 103.752151, "speed": 1, "bearing": 248}, {"bus": "JSX5987", "route": ["P102"], "timestamp": "2023-03-29 21:08:41", "latitude": 1.537285, "longitude": 103.75219, "speed": 1, "bearing": 129}, {"bus": "JSX5997", "route": ["P102"], "timestamp": "2023-03-29 21:51:56", "latitude": 1.537185, "longitude": 103.752151, "speed": 1, "bearing": 180}, {"bus": "JSN4410", "route": ["P102"], "timestamp": "2023-03-29 21:33:03", "latitude": 1.537527, "longitude": 103.752548, "speed": 3, "bearing": 52}, {"bus": "JSC7195", "route": ["P103"], "timestamp": "2023-03-29 20:29:06", "latitude": 1.537397, "longitude": 103.752098, "speed": 4, "bearing": 334}, {"bus": "JSM3203", "route": ["P103"], "timestamp": "2023-03-29 21:40:58", "latitude": 1.537129, "longitude": 103.752281, "speed": 6, "bearing": 139}, {"bus": "JTV3500", "route": ["P104"], "timestamp": "2023-03-28 22:28:07", "latitude": 1.49068, "longitude": 103.72403, "speed": 0, "bearing": 0}, {"bus": "JTQ9300", "route": ["P104"], "timestamp": "2023-03-29 21:04:10", "latitude": 1.490747, "longitude": 103.723991, "speed": 1, "bearing": 14}, {"bus": "JTE9400", "route": ["P106"], "timestamp": "2023-03-05 18:39:04", "latitude": 1.490889, "longitude": 103.72435, "speed": 0, "bearing": 194}, {"bus": "JTE9200", "route": ["P106"], "timestamp": "2023-03-28 21:51:54", "latitude": 1.490701, "longitude": 103.723907, "speed": 1, "bearing": 2}, {"bus": "JTV6100", "route": ["P111"], "timestamp": "2023-03-29 22:14:31", "latitude": 1.490739, "longitude": 103.723969, "speed": 1, "bearing": 355}, {"bus": "JTM3800", "route": ["P112"], "timestamp": "2023-03-28 23:23:46", "latitude": 1.49073, "longitude": 103.724098, "speed": 0, "bearing": 0}, {"bus": "JTU7900", "route": ["P113"], "timestamp": "2023-03-29 22:27:52", "latitude": 1.490707, "longitude": 103.723976, "speed": 1, "bearing": 326}, {"bus": "JSN519", "route": ["P201"], "timestamp": "2023-03-17 03:17:20", "latitude": 1.537145, "longitude": 103.752174, "speed": 0, "bearing": 282}, {"bus": "JSX5982", "route": ["P201"], "timestamp": "2023-03-29 21:36:47", "latitude": 1.537066, "longitude": 103.751915, "speed": 1, "bearing": 264}, {"bus": "JTD3423", "route": ["P202"], "timestamp": "2023-03-29 23:17:10", "latitude": 1.537159, "longitude": 103.75193, "speed": 1, "bearing": 24}, {"bus": "JSP1374", "route": ["P203"], "timestamp": "2023-03-29 20:46:55", "latitude": 1.537373, "longitude": 103.752373, "speed": 1, "bearing": 165}, {"bus": "JSG709", "route": ["P203"], "timestamp": "2023-03-29 21:51:53", "latitude": 1.536358, "longitude": 103.746582, "speed": 3, "bearing": 170}, {"bus": "JSX5418", "route": ["P211"], "timestamp": "2023-03-29 23:43:37", "latitude": 1.537174, "longitude": 103.752113, "speed": 1, "bearing": 66}, {"bus": "JTC9543", "route": ["P211"], "timestamp": "2023-03-29 22:05:25", "latitude": 1.537289, "longitude": 103.752243, "speed": 1, "bearing": 277}, {"bus": "JTV7931", "route": ["P212"], "timestamp": "2023-03-30 00:37:57", "latitude": 1.536127, "longitude": 103.745667, "speed": 0, "bearing": 0}, {"bus": "JTU4288", "route": ["P213"], "timestamp": "2023-03-24 11:28:55", "latitude": 1.521267, "longitude": 103.747978, "speed": 4, "bearing": 273}, {"bus": "JSG6384", "route": ["P214"], "timestamp": "2023-03-29 22:04:18", "latitude": 1.537349, "longitude": 103.752296, "speed": 1, "bearing": 50}, {"bus": "JPX3607", "route": ["P301"], "timestamp": "2023-03-29 08:50:40", "latitude": 1.46587, "longitude": 103.900902, "speed": 2, "bearing": 293}, {"bus": "JNW7297", "route": ["P302"], "timestamp": "2023-03-29 12:00:57", "latitude": 1.481502, "longitude": 103.953667, "speed": 0, "bearing": 311}, {"bus": "JPT4555", "route": ["P302"], "timestamp": "2023-03-27 12:19:45", "latitude": 1.507444, "longitude": 103.746147, "speed": 0, "bearing": 0}, {"bus": "JPX9044", "route": ["P303"], "timestamp": "2023-03-29 19:11:41", "latitude": 1.481849, "longitude": 103.953629, "speed": 0, "bearing": 171}, {"bus": "JPX2419", "route": ["P303"], "timestamp": "2023-03-16 20:47:56", "latitude": 1.507302, "longitude": 103.746651, "speed": 0, "bearing": 267}, {"bus": "JPX3585", "route": ["P311"], "timestamp": "2023-03-02 20:20:07", "latitude": 1.486813, "longitude": 103.885643, "speed": 0, "bearing": 211}, {"bus": "JNW7927", "route": ["P312"], "timestamp": "2023-03-29 21:27:59", "latitude": 1.486652, "longitude": 103.88591, "speed": 15, "bearing": 132}, {"bus": "JPY4982", "route": ["P313"], "timestamp": "2023-03-29 19:40:11", "latitude": 1.598148, "longitude": 103.822304, "speed": 0, "bearing": 73}, {"bus": "JPY4827", "route": ["P314"], "timestamp": "2023-03-29 09:45:05", "latitude": 1.495462, "longitude": 103.944748, "speed": 34, "bearing": 360}, {"bus": "JTU4286", "route": ["P401"], "timestamp": "2023-03-29 20:29:45", "latitude": 1.537128, "longitude": 103.752197, "speed": 12, "bearing": 156}, {"bus": "JTV7929", "route": ["P402"], "timestamp": "2023-03-28 21:14:38", "latitude": 1.537007, "longitude": 103.751961, "speed": 1, "bearing": 141}, {"bus": "JTV7927", "route": ["P403"], "timestamp": "2023-03-29 20:58:19", "latitude": 1.537004, "longitude": 103.751976, "speed": 1, "bearing": 11}, {"bus": "JTV7925", "route": ["P403"], "timestamp": "2023-02-27 09:20:36", "latitude": 1.52142, "longitude": 103.748276, "speed": 0, "bearing": 296}, {"bus": "JSJ7542", "route": ["P411"], "timestamp": "2023-03-29 21:22:25", "latitude": 1.536293, "longitude": 103.746544, "speed": 1, "bearing": 158}, {"bus": "JTU5268", "route": ["P412"], "timestamp": "2023-03-29 21:55:14", "latitude": 1.5371, "longitude": 103.752121, "speed": 8, "bearing": 157}, {"bus": "JSL6461", "route": ["PE001"], "timestamp": "2023-03-29 21:24:55", "latitude": 1.53752, "longitude": 103.752213, "speed": 0, "bearing": 349}, {"bus": "JSY1865", "route": ["PE002"], "timestamp": "2023-03-29 20:37:45", "latitude": 1.552751, "longitude": 104.235901, "speed": 0, "bearing": 137}, {"bus": "JSN4406", "route": ["PE003"], "timestamp": "2023-03-20 11:59:52", "latitude": 1.554869, "longitude": 104.228706, "speed": 0, "bearing": 13}, {"bus": "JSJ6534", "route": ["PE004"], "timestamp": "2023-03-29 20:27:31", "latitude": 1.552708, "longitude": 104.235886, "speed": 1, "bearing": 90}, {"bus": "JSU4727", "route": ["PE005"], "timestamp": "2023-03-29 20:03:09", "latitude": 1.552764, "longitude": 104.235939, "speed": 0, "bearing": 252}, {"bus": "JQU5545", "route": ["PN001"], "timestamp": "2023-03-29 15:51:04", "latitude": 1.478479, "longitude": 103.39122, "speed": 39, "bearing": 260}, {"bus": "JUQ5545", "route": ["PN002"], "timestamp": "2023-03-29 18:53:01", "latitude": 1.516928, "longitude": 103.575478, "speed": 36, "bearing": 1}, {"bus": "VDU5595", "route": ["SE001"], "timestamp": "2023-03-29 19:03:24", "latitude": 2.508532, "longitude": 102.812912, "speed": 1, "bearing": 193}, {"bus": "FB9311", "route": ["SE002", "SE003"], "timestamp": "2023-03-29 20:08:40", "latitude": 2.508271, "longitude": 102.813156, "speed": 4, "bearing": 189}, {"bus": "JNT2686", "route": ["SR001"], "timestamp": "2023-03-29 18:41:15", "latitude": 1.825816, "longitude": 103.310104, "speed": 2, "bearing": 124}, {"bus": "JTY5545", "route": ["SR002"], "timestamp": "2023-03-29 19:11:21", "latitude": 1.825809, "longitude": 103.310135, "speed": 1, "bearing": 141}, {"bus": "JUG5554", "route": ["SR003"], "timestamp": "2023-03-29 18:49:49", "latitude": 1.82587, "longitude": 103.31012, "speed": 3, "bearing": 124}, {"bus": "JQU5554", "route": ["SR004"], "timestamp": "2023-03-29 18:16:54", "latitude": 1.885225, "longitude": 103.402771, "speed": 23, "bearing": 180}, {"bus": "JSB1200", "route": ["TK001", "TK001A"], "timestamp": "2023-03-29 16:20:29", "latitude": 2.280226, "longitude": 102.543526, "speed": 25, "bearing": 171}, {"bus": "JSY2500", "route": ["TK002"], "timestamp": "2023-03-26 10:50:14", "latitude": 2.04663, "longitude": 102.564911, "speed": 0, "bearing": 101}, {"bus": "VAC6500", "route": ["YP001"], "timestamp": "2023-03-29 18:36:48", "latitude": 2.003284, "longitude": 103.068436, "speed": 3, "bearing": 152}]}